bambulabs_api/__init__.py
bambulabs_api/ams.py
bambulabs_api/camera_client.py
bambulabs_api/client.py
bambulabs_api/filament_info.py
bambulabs_api/ftp_client.py
bambulabs_api/mqtt_client.py
bambulabs_api/printer_info.py
bambulabs_api/py.typed
bambulabs_api/states_info.py
bambulabs_api-2.6.4.dist-info/licenses/LICENSE
bambulabs_api-2.6.4.dist-info/METADATA
bambulabs_api-2.6.4.dist-info/WHEEL
bambulabs_api-2.6.4.dist-info/top_level.txt
bambulabs_api-2.6.4.dist-info/RECORD
