Metadata-Version: 2.4
Name: bambulabs_api
Version: 2.6.4
Summary: API for BambuLab 3D Printers over MQTT
Home-page: https://github.com/acse-ci223/bambulabs_api
Author: Chris Ioannidis
Author-email: Chris Ioannidis <chris.ioannidis23@imperial.ac.uk>, Haotian Wu <64962148+ohmdelta@users.noreply.github.com>
Project-URL: Homepage, https://github.com/BambuTools/bambulabs_api
Project-URL: Docs, https://bambutools.github.io/bambulabs_api/
Project-URL: Issues, https://github.com/BambuTools/bambulabs_api/issues
Classifier: Programming Language :: Python :: 3
Classifier: License :: OSI Approved :: MIT License
Classifier: Operating System :: OS Independent
Requires-Python: >=3.10
License-File: LICENSE
Requires-Dist: paho-mqtt>=2.0.0
Requires-Dist: pillow>=11.0.0
Dynamic: author
Dynamic: home-page
Dynamic: license-file
